write_a_thing/__init__.py
write_a_thing/cli.py
write_a_thing/tools.py
write_a_thing/writing.py
write_a_thing-0.3.0.dist-info/METADATA
write_a_thing-0.3.0.dist-info/WHEEL
write_a_thing-0.3.0.dist-info/entry_points.txt
write_a_thing-0.3.0.dist-info/licenses/LICENSE
write_a_thing-0.3.0.dist-info/RECORD
