Metadata-Version: 2.4
Name: write_a_thing
Version: 0.3.0
Summary: Use LLMs to help you write your things.
Project-URL: Repository, https://github.com/alexandrainst/write_a_thing
Project-URL: Issues, https://github.com/alexandrainst/write_a_thing/issues
Author-email: Dan Saattrup Nielsen <dan.nielsen@alexandra.dk>
Maintainer-email: Dan Saattrup Nielsen <dan.nielsen@alexandra.dk>
License: MIT License
License-File: LICENSE
Requires-Python: <4.0,>=3.11
Requires-Dist: click>=8.2.1
Requires-Dist: docling>=2.31.1
Requires-Dist: emoji>=2.14.1
Requires-Dist: litellm>=1.71.1
Requires-Dist: pypandoc>=1.15
Requires-Dist: smolagents>=1.16.1
